paka/__init__.py
paka/cli/__init__.py
paka/cli/__main__.py
paka/cli/build.py
paka/cli/cluster.py
paka/cli/function.py
paka/cli/job.py
paka/cli/kubeconfig.py
paka/cli/model_group.py
paka/cli/run.py
paka/cli/utils.py
paka/cluster/__init__.py
paka/cluster/aws/__init__.py
paka/cluster/aws/cloudwatch.py
paka/cluster/aws/cluster_autoscaler.py
paka/cluster/aws/container_registry.py
paka/cluster/aws/ebs_csi_driver.py
paka/cluster/aws/eks.py
paka/cluster/aws/elb.py
paka/cluster/aws/object_store.py
paka/cluster/aws/service_account.py
paka/cluster/aws/utils.py
paka/cluster/context.py
paka/cluster/fluentbit.py
paka/cluster/keda.py
paka/cluster/knative.py
paka/cluster/kubectl.py
paka/cluster/manager/__init__.py
paka/cluster/manager/aws.py
paka/cluster/manager/base.py
paka/cluster/namespace.py
paka/cluster/nvidia_device_plugin.py
paka/cluster/prometheus.py
paka/cluster/pulumi.py
paka/cluster/qdrant.py
paka/cluster/redis.py
paka/cluster/utils.py
paka/cluster/zipkin.py
paka/config.py
paka/constants.py
paka/container/ecr.py
paka/container/pack.py
paka/gguf.py
paka/k8s/function/__init__.py
paka/k8s/function/service.py
paka/k8s/job/__init__.py
paka/k8s/job/autoscaler.py
paka/k8s/job/worker.py
paka/k8s/model_group/__init__.py
paka/k8s/model_group/ingress.py
paka/k8s/model_group/manifest.py
paka/k8s/model_group/runtime/__init__.py
paka/k8s/model_group/runtime/llama_cpp.py
paka/k8s/model_group/runtime/vllm.py
paka/k8s/model_group/service.py
paka/k8s/model_group/service_v1.py
paka/k8s/utils.py
paka/logger.py
paka/model/__init__.py
paka/model/base_model.py
paka/model/hf_model.py
paka/model/http_model.py
paka/model/manifest.py
paka/model/progress_bar.py
paka/model/settings.py
paka/model/store.py
paka/utils.py
paka-0.1.11.dist-info/LICENSE
paka-0.1.11.dist-info/METADATA
paka-0.1.11.dist-info/WHEEL
paka-0.1.11.dist-info/entry_points.txt
paka-0.1.11.dist-info/RECORD
