Metadata-Version: 2.1
Name: paka
Version: 0.1.11
Summary: LLMOps tool designed to simplify the deployment and management of large language model (LLM) applications
Home-page: https://github.com/jjleng/paka
Keywords: LLMOps,RAG,production,Cloud
Author: Jijun Leng
Requires-Python: >=3.8,<4.0
Classifier: Programming Language :: Python :: 3
Classifier: Programming Language :: Python :: 3.8
Classifier: Programming Language :: Python :: 3.9
Classifier: Programming Language :: Python :: 3.10
Classifier: Programming Language :: Python :: 3.11
Classifier: Programming Language :: Python :: 3.12
Requires-Dist: boto3 (>=1.34.86,<2.0.0)
Requires-Dist: fasteners (>=0.19,<0.20)
Requires-Dist: huggingface-hub (>=0.22.2,<0.23.0)
Requires-Dist: kubernetes (>=29.0.0,<30.0.0)
Requires-Dist: pathspec (>=0.12.1,<0.13.0)
Requires-Dist: pulumi (==3.105.0)
Requires-Dist: pulumi-aws (>=6.31.0,<7.0.0)
Requires-Dist: pulumi-awsx (>=2.7.0,<3.0.0)
Requires-Dist: pulumi-eks (>=2.3.0,<3.0.0)
Requires-Dist: pulumi-kubernetes (>=4.8.1,<5.0.0)
Requires-Dist: pydantic (>=2.7.0,<3.0.0)
Requires-Dist: requests (>=2.31.0,<3.0.0)
Requires-Dist: ruamel-yaml (>=0.18.6,<0.19.0)
Requires-Dist: tabulate (>=0.9.0,<0.10.0)
Requires-Dist: tenacity (>=8.2.3,<9.0.0)
Requires-Dist: tqdm (>=4.66.2,<5.0.0)
Requires-Dist: typer (>=0.12.3,<0.13.0)
Requires-Dist: typing-extensions (>=4.11.0,<5.0.0)
